tier/__init__.py
tier-0.0.0.dist-info/LICENSE
tier-0.0.0.dist-info/WHEEL
tier-0.0.0.dist-info/METADATA
tier-0.0.0.dist-info/RECORD
