Metadata-Version: 2.1
Name: tier
Version: 0.0.0
Summary: Python Versioning CLI
License: MIT
Author: Josh Wycuff
Author-email: Joshua.Wycuff@turner.com
Requires-Python: >=3.7,<4
Classifier: License :: OSI Approved :: MIT License
Classifier: Programming Language :: Python :: 3
Classifier: Programming Language :: Python :: 3.7
Classifier: Programming Language :: Python :: 3.8
Classifier: Programming Language :: Python :: 3.9
Classifier: Programming Language :: Python :: 3.10
